src/__init__.py
src/__init__.pyi
src/__main__.py
src/cli.py
src/sequential_story_processor.py
src/sequential_thinking_processor.py
src/server.py
src/utils/__init__.py
src/utils/__init__.pyi
src/utils/logging.py
src/utils/settings.py
sequential_story-1.0.1.dist-info/METADATA
sequential_story-1.0.1.dist-info/WHEEL
sequential_story-1.0.1.dist-info/entry_points.txt
sequential_story-1.0.1.dist-info/RECORD
