Metadata-Version: 2.4
Name: sequential-story
Version: 1.0.1
Summary: A sequential storytelling MCP server for mnemonic problem-solving
Project-URL: Homepage, https://github.com/dhkts1/sequentialStory
Project-URL: Repository, https://github.com/dhkts1/sequentialStory
Project-URL: Documentation, https://github.com/dhkts1/sequentialStory/blob/main/README.md
Author: dhkts1
License: MIT
Keywords: llm,mcp,sequential-story,sequential-thinking,storytelling
Classifier: Development Status :: 4 - Beta
Classifier: Intended Audience :: Developers
Classifier: Programming Language :: Python :: 3
Classifier: Programming Language :: Python :: 3.11
Requires-Python: >=3.11
Requires-Dist: lazy-loader>=0.4
Requires-Dist: mcp[cli]>=1.5.0
Requires-Dist: pydantic-settings>=2.8.1
Requires-Dist: rich>=13.7.0
